{
    "player_level": 1,
    "position": "center",
    "pos_sorted": 5,
    "player_name": "xChxmpz--",
    "client_platform": "ps5",
    "player_level_display": 299,
    "is_guest": 0,
    "player_dnf": 0,
    "pnhl_online_game_type": "5",
    "team_id": 501,
    "team_side": 1,
    "opponent_club_id": "29557",
    "opponent_team_id": 500,
    "opponent_score": 4,
    "score": 6,
    "rating_defense": 95.0,
    "rating_offense": 100.0,
    "rating_teamplay": 75.0,
    "toi": 60,
    "toi_seconds": 3600,
    "skassists": 4,
    "skbs": 2,
    "skdeflections": 0,
    "skfol": 13,
    "skfopct": 40.91,
    "skfow": 9,
    "skgiveaways": 6,
    "skgoals": 1,
    "skgwg": 0,
    "skhits": 3,
    "skinterceptions": 5,
    "skpassattempts": 19,
    "skpasses": 15,
    "skpasspct": 78.95,
    "skpenaltiesdrawn": 1,
    "skpim": 0,
    "skpkclearzone": 0,
    "skplusmin": 3,
    "skpossession": 143,
    "skppg": 0,
    "sksaucerpasses": 1,
    "skshg": 0,
    "skshotattempts": 2,
    "skshotonnetpct": 50.0,
    "skshotpct": 100.0,
    "skshots": 1,
    "sktakeaways": 3,
    "glbrksavepct": 0.0,
    "glbrksaves": 0,
    "glbrkshots": 0,
    "gldsaves": 0,
    "glga": 0,
    "glgaa": 0.0,
    "glpensavepct": 0.0,
    "glpensaves": 0,
    "glpenshots": 0,
    "glpkclearzone": 0,
    "glpokechecks": 0,
    "glsavepct": 0.0,
    "glsaves": 0,
    "glshots": 0,
    "glsoperiods": 0,
    "points": 5,
    "faceoffs_total": 22,
    "faceoff_percentage": 40.91,
    "shots_missed": 1,
    "shooting_percentage": 100.0,
    "passes_missed": 4,
    "passing_percentage": 78.95,
    "goals_saved": null,
    "save_percentage": null,
    "major_penalties": 0,
    "minor_penalties": 0,
    "total_penalties": 0,
    "points_per_60": 5.0,
    "possession_per_minute": 2.38,
    "shot_efficiency": 50.0,
    "takeaway_giveaway_ratio": 0.5,
    "penalty_differential": 1,
    "defensive_actions_per_minute": 0.13,
    "offensive_impact": 0.11,
    "defensive_impact": 0.03,
    "detailed_position": "center",
    "position_abbreviation": "C",
    "game_impact_score": 7.1,
    "puck_management_rating": 4.3,
    "possession_efficiency": 2.1,
    "net_defensive_contribution": 4,
    "time_adjusted_rating": 135.0,
    "shot_generation_rate": 0.03,
    "offensive_zone_presence": 3.7,
    "two_way_rating": 4.8,
    "match_id": "24238589020211",
    "club_id": "35362",
    "player_id": "1765926580",
    "game_result": "win",
    "home_away": "away"
}