{
    "player_level": 6,
    "position": "center",
    "pos_sorted": 5,
    "player_name": "Mantzzzy",
    "client_platform": "xbsx",
    "player_level_display": 150,
    "is_guest": 0,
    "player_dnf": 0,
    "pnhl_online_game_type": "5",
    "team_id": 500,
    "team_side": 0,
    "opponent_club_id": "35362",
    "opponent_team_id": 501,
    "opponent_score": 3,
    "score": 0,
    "rating_defense": 80.0,
    "rating_offense": 75.0,
    "rating_teamplay": 70.0,
    "toi": 50,
    "toi_seconds": 3007,
    "skassists": 1,
    "skbs": 0,
    "skdeflections": 1,
    "skfol": 10,
    "skfopct": 33.33,
    "skfow": 5,
    "skgiveaways": 4,
    "skgoals": 1,
    "skgwg": 0,
    "skhits": 6,
    "skinterceptions": 4,
    "skpassattempts": 7,
    "skpasses": 6,
    "skpasspct": 85.71,
    "skpenaltiesdrawn": 0,
    "skpim": 0,
    "skpkclearzone": 0,
    "skplusmin": 1,
    "skpossession": 183,
    "skppg": 0,
    "sksaucerpasses": 0,
    "skshg": 0,
    "skshotattempts": 2,
    "skshotonnetpct": 100.0,
    "skshotpct": 50.0,
    "skshots": 2,
    "sktakeaways": 2,
    "glbrksavepct": 0.0,
    "glbrksaves": 0,
    "glbrkshots": 0,
    "gldsaves": 0,
    "glga": 0,
    "glgaa": 0.0,
    "glpensavepct": 0.0,
    "glpensaves": 0,
    "glpenshots": 0,
    "glpkclearzone": 0,
    "glpokechecks": 0,
    "glsavepct": 0.0,
    "glsaves": 0,
    "glshots": 0,
    "glsoperiods": 0,
    "points": 2,
    "faceoffs_total": 15,
    "faceoff_percentage": 33.33,
    "shots_missed": 0,
    "shooting_percentage": 50.0,
    "passes_missed": 1,
    "passing_percentage": 85.71,
    "goals_saved": null,
    "save_percentage": null,
    "major_penalties": 0,
    "minor_penalties": 0,
    "total_penalties": 0,
    "points_per_60": 2.4,
    "possession_per_minute": 3.66,
    "shot_efficiency": 50.0,
    "takeaway_giveaway_ratio": 0.5,
    "penalty_differential": 0,
    "defensive_actions_per_minute": 0.16,
    "offensive_impact": 0.08,
    "defensive_impact": 0.08,
    "detailed_position": "center",
    "position_abbreviation": "C",
    "game_impact_score": 5.1,
    "puck_management_rating": 4.4,
    "possession_efficiency": 0.66,
    "net_defensive_contribution": 2,
    "time_adjusted_rating": 112.5,
    "shot_generation_rate": 0.04,
    "offensive_zone_presence": 3.8,
    "two_way_rating": 3.0,
    "match_id": "24294805730485",
    "club_id": "45048",
    "player_id": "1003743894922",
    "game_result": "loss",
    "home_away": "home"
}